app_onnx/__init__.py
app_onnx/main.py
app_onnx/main_window.py
app_onnx/workers/__init__.py
app_onnx/workers/chart_worker.py
app_onnx/workers/detection_worker.py
app_onnx/workers/yoloworld_onnx.py
app_onnx/workers/utils/__init__.py
app_onnx/workers/utils/chart_utils.py
app_onnx/workers/utils/detection_utils.py
app_onnx/workers/utils/draw_utils.py
app_onnx/workers/utils/write_utils.py
odlabel_onnx-0.7.26.9.dist-info/METADATA
odlabel_onnx-0.7.26.9.dist-info/WHEEL
odlabel_onnx-0.7.26.9.dist-info/entry_points.txt
odlabel_onnx-0.7.26.9.dist-info/top_level.txt
odlabel_onnx-0.7.26.9.dist-info/RECORD
