Metadata-Version: 2.1
Name: odlabel-onnx
Version: 0.7.26.9
Summary: A tool for object detection, labeling and visualization using ONNX
Home-page: https://github.com/Ziad-Algrafi/odlabel
Author: Ziad-Algrafi
Author-email: ZiadAlgrafi@gmail.com
Classifier: Development Status :: 4 - Beta
Classifier: Intended Audience :: Developers
Classifier: License :: OSI Approved :: GNU Affero General Public License v3
Classifier: Programming Language :: Python :: 3
Classifier: Programming Language :: Python :: 3.9
Classifier: Programming Language :: Python :: 3.10
Classifier: Programming Language :: Python :: 3.11
Classifier: Programming Language :: Python :: 3.12
Requires-Python: >=3.9
Requires-Dist: setuptools ==69.5.1
Requires-Dist: wheel ==0.43.0
Requires-Dist: customtkinter
Requires-Dist: matplotlib
Requires-Dist: numpy
Requires-Dist: opencv-python
Requires-Dist: onnxruntime-gpu
Requires-Dist: torch >=1.7.0
Requires-Dist: torchvision >=0.8.0
Requires-Dist: clip-for-odlabel
